larry/__init__.py
larry/_in_vitro.py
larry/_LightningDataModule/_LARRY_LightningDataModule.py
larry/_LightningDataModule/__init__.py
larry/_LightningDataModule/_supporting_functions/__init__.py
larry/_LightningDataModule/_supporting_functions/_adata_formatting.py
larry/_LightningDataModule/_supporting_functions/_annotate_task_groups.py
larry/_LightningDataModule/_supporting_functions/_download_LARRY_in_vitro.py
larry/_LightningDataModule/_supporting_functions/_format_time.py
larry/_LightningDataModule/_supporting_functions/_split_training_data.py
larry/_data/LARRY.in_vitro.X_fate.npy
larry/_data/LARRY.in_vitro.d2_fate_biases.csv
larry/_data/LARRY_PathDict.pkl
larry/_data/early_cells.npy
larry/_data/early_neu_mo.npy
larry/_data/fate_score.npy
larry/_data/growth_score.npy
larry/_data/neu_mo_mask.npy
larry/_data/neu_vs_mo_pct.npy
larry/_fetch/__init__.py
larry/_fetch/_fetch_data_from_github.py
larry/_preprocess/_Yeo2021_preprocessing_recipe.py
larry/_preprocess/__init__.py
larry/_preprocess/_add_data_from_supp_files.py
larry/_preprocess/_annotate_test_train.py
larry/_preprocess/_build_kNN.py
LARRY_dataset-0.0.1.dist-info/LICENSE
LARRY_dataset-0.0.1.dist-info/METADATA
LARRY_dataset-0.0.1.dist-info/WHEEL
LARRY_dataset-0.0.1.dist-info/top_level.txt
LARRY_dataset-0.0.1.dist-info/RECORD
