Metadata-Version: 2.1
Name: LARRY-dataset
Version: 0.0.1
Summary: LARRY Dataset: lineage and RNA recovery
Home-page: https://github.com/pinellolab/LARRY-dataset
Author: Michael E. Vinyard - Harvard University - Massachussetts General Hospital - Broad Institute of MIT and Harvard
Author-email: mvinyard@broadinstitute.org
License: MIT
Classifier: Development Status :: 2 - Pre-Alpha
Classifier: Programming Language :: Python :: 3.7
Classifier: Intended Audience :: Science/Research
Classifier: Topic :: Scientific/Engineering :: Bio-Informatics
Requires-Python: >3.7.0
License-File: LICENSE
Requires-Dist: anndata (>=0.8)
Requires-Dist: pytorch-lightning (>=1.7.5)
Requires-Dist: wget (>=3.2)
